errorreport
