Metadata-Version: 1.0
Name: ErrorReport
Version: 0.3.2
Summary: Provide HTML error reports during development of web applications and email reports for errors occurring in production.
Home-page: http://jimmyg.org/work/code/errorreport/index.html
Author: James Gardner
Author-email: UNKNOWN
License: GNU AGPLv3
Platform: UNKNOWN
Classifier: Development Status :: 3 - Alpha
Classifier: License :: OSI Approved :: GNU Affero General Public License v3
Classifier: Programming Language :: Python :: 2
Classifier: Topic :: Software Development :: Libraries :: Python Modules
Classifier: Environment :: Web Environment
